findfivers/__main__.py
findfivers/custom_argparse.py
findfivers-0.4.0.dist-info/LICENSE
findfivers-0.4.0.dist-info/METADATA
findfivers-0.4.0.dist-info/WHEEL
findfivers-0.4.0.dist-info/RECORD
