Metadata-Version: 2.1
Name: findfivers
Version: 0.4.0
Summary: select five(default)-letter words from a source text
License: MIT
Keywords: text,word,length
Author: Attila Novak
Author-email: bajni37@gmail.com
Requires-Python: >=3.12,<4.0
Classifier: License :: OSI Approved :: MIT License
Classifier: Programming Language :: Python
Classifier: Programming Language :: Python :: 3
Classifier: Programming Language :: Python :: 3.12
Requires-Dist: pandas (>=2.2.2,<3.0.0)
